log_surgeon_ffi.cpython-311-i386-linux-gnu.so
log_surgeon_ffi-0.1.0b8.dist-info/RECORD
log_surgeon_ffi-0.1.0b8.dist-info/WHEEL
log_surgeon_ffi-0.1.0b8.dist-info/METADATA
log_surgeon_ffi-0.1.0b8.dist-info/licenses/LICENSE
log_surgeon/log_event.py
log_surgeon/query.py
log_surgeon/__init__.py
log_surgeon/variable.py
log_surgeon/parser.py
log_surgeon/py.typed
log_surgeon/reader_parser.pyi
log_surgeon/pattern.py
log_surgeon/schema_compiler.py
log_surgeon_ffi/PyReaderParser.cpp
log_surgeon_ffi/PyExceptionContext.hpp
log_surgeon_ffi/utils.cpp
log_surgeon_ffi/PyObjectCast.hpp
log_surgeon_ffi/log_surgeon_ffi.cpp
log_surgeon_ffi/PyReaderParser.hpp
log_surgeon_ffi/utils.hpp
log_surgeon_ffi/PyObjectUtils.hpp
log_surgeon_ffi/api_decoration.hpp
