Metadata-Version: 2.2
Name: log-surgeon-ffi
Version: 0.1.0b8
Summary: Python FFI bindings for log-surgeon: high-performance parsing of unstructured logs into structured data
Keywords: logging,log-parsing,log-analysis,structured-data,performance,observability
Author-Email: y-scope <info@yscope.com>
License: Apache License 2.0
Classifier: Development Status :: 4 - Beta
Classifier: Intended Audience :: Developers
Classifier: Intended Audience :: System Administrators
Classifier: License :: OSI Approved :: Apache Software License
Classifier: Programming Language :: Python :: 3
Classifier: Programming Language :: Python :: 3.9
Classifier: Programming Language :: Python :: 3.10
Classifier: Programming Language :: Python :: 3.11
Classifier: Programming Language :: Python :: 3.12
Classifier: Programming Language :: Python :: 3.13
Classifier: Programming Language :: C++
Classifier: Topic :: Software Development :: Libraries :: Python Modules
Classifier: Topic :: System :: Logging
Classifier: Topic :: System :: Monitoring
Classifier: Operating System :: POSIX :: Linux
Project-URL: Homepage, https://github.com/y-scope/log-surgeon-ffi-py
Project-URL: Bug Tracker, https://github.com/y-scope/log-surgeon-ffi-py/issues
Requires-Python: >=3.9
Requires-Dist: pandas>=2.0.0
Requires-Dist: pyarrow>=14.0.0
Provides-Extra: dataframe
Requires-Dist: pandas>=2.0.0; extra == "dataframe"
Provides-Extra: arrow
Requires-Dist: pyarrow>=14.0.0; extra == "arrow"
Provides-Extra: all
Requires-Dist: pandas>=2.0.0; extra == "all"
Requires-Dist: pyarrow>=14.0.0; extra == "all"
